kr_school_meal/__init__.py
kr_school_meal/meal.py
kr_school_meal/neis_code.py
kr_school_meal-0.0.2.dist-info/LICENSE
kr_school_meal-0.0.2.dist-info/METADATA
kr_school_meal-0.0.2.dist-info/WHEEL
kr_school_meal-0.0.2.dist-info/top_level.txt
kr_school_meal-0.0.2.dist-info/RECORD
