Metadata-Version: 2.1
Name: kr-school-meal
Version: 0.0.2
Summary: Korea School Meal
Home-page: https://github.com/moseoridev/korea-school-meal
Author: moseoridev
Author-email: sjssjs1344@gmail.com
License: UNKNOWN
Platform: UNKNOWN
Classifier: Programming Language :: Python :: 3
Classifier: License :: OSI Approved :: Mozilla Public License 2.0 (MPL 2.0)
Classifier: Operating System :: OS Independent
Classifier: Natural Language :: Korean
Requires-Python: >=3.6
